setup.cfg
setup.py
codon_tools/__init__.py
codon_tools/codon_analyzer.py
codon_tools/codon_optimizer.py
codon_tools/codon_shuffler.py
codon_tools/lookup_tables.py
codon_tools/scorer.py
codon_tools/sequence_analyzer.py
codon_tools.egg-info/PKG-INFO
codon_tools.egg-info/SOURCES.txt
codon_tools.egg-info/dependency_links.txt
codon_tools.egg-info/requires.txt
codon_tools.egg-info/top_level.txt