Metadata-Version: 1.0
Name: codon-tools
Version: 0.2
Summary: Toolkit to manipulate synonymous codon usage in various ways
Home-page: http://github.com/clauswilke/codon_tools
Author: Claus O. Wilke
Author-email: wilke@austin.utexas.edu
License: MIT
Platform: UNKNOWN
